rick_roll.py
rick_roll-0.0.3.dist-info/LICENSE
rick_roll-0.0.3.dist-info/METADATA
rick_roll-0.0.3.dist-info/WHEEL
rick_roll-0.0.3.dist-info/top_level.txt
rick_roll-0.0.3.dist-info/RECORD
