Metadata-Version: 2.1
Name: rick-roll
Version: 0.0.3
Summary: Module for your rickrolling needs which will never let you down.
Home-page: https://github.com/screechingviolet/rick-roll
Author: Aanya Agrawal
License: UNKNOWN
Platform: UNKNOWN
Classifier: Programming Language :: Python :: 3
Classifier: License :: OSI Approved :: MIT License
Classifier: Operating System :: OS Independent
Requires-Python: >=3.7
License-File: LICENSE
